[
  {
    "Id": "9AEE900E-EE8C-4C72-9D5B-05D8AA6657BF",
    "Name": "Property-Name-0001",
    "Address": "Property-Address-0001",
    "Description": "Property-Description-0001-Sample-Data",
    "SquareMeter": 320.50,
    "NumberRooms": 5,
    "NumberBathrooms": 3,
    "PropertyTypeId": "2E191A01-5623-4C92-B9DF-811955F990E8", //Change Guid Propety Type
    "SalePrice": 250000.00,
    "RentPrice": 700.00,
    "SaleTax": 15.00,
    "IncomeTax": 10.00,
    "CodeInternal": "PCI0000001",
    "Year": 2005,
    "HasParking": true,
    "IsActive": true,
    "OwnerId": "41C43138-9280-4EDC-9307-BEBE359796A5"
  },
  {
    "Id": "E2885DB2-1310-4A2D-B109-42934DE3046A",
    "Name": "Property-Name-0002",
    "Address": "Property-Address-0002",
    "Description": "Property-Description-0002-Sample-Data",
    "SquareMeter": 280.78,
    "NumberRooms": 3,
    "NumberBathrooms": 1,
    "PropertyTypeId": "3CCA2E47-C344-4E6D-98C2-57FE35FC0F35", //Change Guid Propety Type
    "SalePrice": 250000.00,
    "RentPrice": 700.00,
    "SaleTax": 15.00,
    "IncomeTax": 10.00,
    "CodeInternal": "PCI0000002",
    "Year": 2006,
    "HasParking": false,
    "IsActive": true,
    "OwnerId": "D0C11FF5-02AB-440A-966C-6AA5EDA9B2BB"
  },
  {
    "Id": "0B96982E-A85A-4816-B33F-15B287E29F0C",
    "Name": "Property-Name-0003",
    "Address": "Property-Address-0003",
    "Description": "Property-Description-0003-Sample-Data",
    "SquareMeter": 250.42,
    "NumberRooms": 3,
    "NumberBathrooms": 1,
    "PropertyTypeId": "35E9F237-FB6E-4E8E-B2C5-B5255C24801F",
    "SalePrice": 250000.00,
    "RentPrice": 700.00,
    "SaleTax": 15.00,
    "IncomeTax": 10.00,
    "CodeInternal": "PCI0000003",
    "Year": 2007,
    "HasParking": true,
    "IsActive": true,
    "OwnerId": "0C3A18AC-068D-41C2-BA37-4CA1BCD6F9F7"
  },
  {
    "Id": "90F1B249-B7FF-4130-BE5B-BC3CC977EA16",
    "Name": "Property-Name-0004",
    "Address": "Property-Address-0004",
    "Description": "Property-Description-0004-Sample-Data",
    "SquareMeter": 450.36,
    "NumberRooms": 3,
    "NumberBathrooms": 1,
    "PropertyTypeId": "4F426DDE-E40C-4819-97B5-AEF5F94A5D53",
    "SalePrice": 250000.00,
    "RentPrice": 700.00,
    "SaleTax": 15.00,
    "IncomeTax": 10.00,
    "CodeInternal": "PCI0000004",
    "Year": 2001,
    "HasParking": true,
    "IsActive": true,
    "OwnerId": "6449C449-59DA-4C60-9AB2-1B9949024C86"
  },
  {
    "Id": "57E43EDA-872F-4E27-9B6E-E335C9C7C8DC",
    "Name": "Property-Name-0005",
    "Address": "Property-Address-0005",
    "Description": "Property-Description-0005-Sample-Data",
    "SquareMeter": 192.25,
    "NumberRooms": 3,
    "NumberBathrooms": 1,
    "PropertyTypeId": "16E5767E-F9D5-410B-B4AD-C9776E8712F2",
    "SalePrice": 250000.00,
    "RentPrice": 700.00,
    "SaleTax": 15.00,
    "IncomeTax": 10.00,
    "CodeInternal": "PCI0000005",
    "Year": 2002,
    "HasParking": false,
    "IsActive": true,
    "OwnerId": "8B7CECC3-E157-419A-AA14-99D5A3C934A0"
  },
  {
    "Id": "4E9614BB-B3C2-4772-AE67-1B0EC1EACB80",
    "Name": "Property-Name-0006",
    "Address": "Property-Address-0006",
    "Description": "Property-Description-0006-Sample-Data",
    "SquareMeter": 192.25,
    "NumberRooms": 3,
    "NumberBathrooms": 1,
    "PropertyTypeId": "7E8DFFC0-558E-4133-8386-DDB33B716AF4",
    "SalePrice": 250000.00,
    "RentPrice": 700.00,
    "SaleTax": 15.00,
    "IncomeTax": 10.00,
    "CodeInternal": "PCI0000006",
    "Year": 2003,
    "HasParking": true,
    "IsActive": true,
    "OwnerId": "A0FEA333-5986-42F8-8B3D-2EF65D85F1B8"
  },
  {
    "Id": "C4C69DFC-90F8-4D73-9F2C-580703ACCDD6",
    "Name": "Property-Name-0007",
    "Address": "Property-Address-0007",
    "Description": "Property-Description-0007-Sample-Data",
    "SquareMeter": 192.25,
    "NumberRooms": 3,
    "NumberBathrooms": 1,
    "PropertyTypeId": "35E9F237-FB6E-4E8E-B2C5-B5255C24801F",
    "SalePrice": 250000.00,
    "RentPrice": 700.00,
    "SaleTax": 15.00,
    "IncomeTax": 10.00,
    "CodeInternal": "PCI0000007",
    "Year": 2004,
    "HasParking": true,
    "IsActive": true,
    "OwnerId": "4FFCF2CC-9229-47B8-8F21-6654CDA47E2A"
  },
  {
    "Id": "66848F7C-067A-4B7A-8D01-EABAB85D9E98",
    "Name": "Property-Name-0008",
    "Address": "Property-Address-0008",
    "Description": "Property-Description-0008-Sample-Data",
    "SquareMeter": 192.25,
    "NumberRooms": 3,
    "NumberBathrooms": 1,
    "PropertyTypeId": "92E2453A-7D2F-44A4-A9FB-3E11ED3BB458",
    "SalePrice": 250000.00,
    "RentPrice": 700.00,
    "SaleTax": 15.00,
    "IncomeTax": 10.00,
    "CodeInternal": "PCI0000008",
    "Year": 2008,
    "HasParking": true,
    "IsActive": true,
    "OwnerId": "0021CE10-1203-4459-A685-9F8698DA19CE"
  },
  {
    "Id": "3E82159C-2B9F-4D91-9268-7618742BF517",
    "Name": "Property-Name-0009",
    "Address": "Property-Address-0009",
    "Description": "Property-Description-0009-Sample-Data",
    "SquareMeter": 192.25,
    "NumberRooms": 3,
    "NumberBathrooms": 1,
    "PropertyTypeId": "F4E25DF1-82C4-4685-91AC-7305F6EB9ADD",
    "SalePrice": 250000.00,
    "RentPrice": 700.00,
    "SaleTax": 15.00,
    "IncomeTax": 10.00,
    "CodeInternal": "PCI0000009",
    "Year": 2009,
    "HasParking": false,
    "IsActive": true,
    "OwnerId": "E5C3D9B5-5988-48C6-96A3-02E680E48234"
  },
  {
    "Id": "A1D8D88D-2C85-4B25-8C37-555F23E7FFBF",
    "Name": "Property-Name-0010",
    "Address": "Property-Address-0010",
    "Description": "Property-Description-0010-Sample-Data",
    "SquareMeter": 192.25,
    "NumberRooms": 3,
    "NumberBathrooms": 1,
    "PropertyTypeId": "F4E25DF1-82C4-4685-91AC-7305F6EB9ADD",
    "SalePrice": 250000.00,
    "RentPrice": 700.00,
    "SaleTax": 15.00,
    "IncomeTax": 10.00,
    "CodeInternal": "PCI0000010",
    "Year": 2010,
    "HasParking": false,
    "IsActive": true,
    "OwnerId": "38440EEA-FC9F-4B6F-B623-F72FDDC66A29"
  },
  {
    "Id": "D4FBB6BC-60B9-440B-9856-B40F6ADAC10B",
    "Name": "Property-Name-0101",
    "Address": "Property-Address-0101",
    "Description": "Property-Description-0101-Sample-Data",
    "SquareMeter": 192.25,
    "NumberRooms": 3,
    "NumberBathrooms": 1,
    "PropertyTypeId": "92E2453A-7D2F-44A4-A9FB-3E11ED3BB458",
    "SalePrice": 250000.00,
    "RentPrice": 700.00,
    "SaleTax": 15.00,
    "IncomeTax": 10.00,
    "CodeInternal": "PCI0000101",
    "Year": 2011,
    "HasParking": true,
    "IsActive": true,
    "OwnerId": "D0C11FF5-02AB-440A-966C-6AA5EDA9B2BB"
  },
  {
    "Id": "2A2D5DE2-3AD3-4407-983F-26A5E6CD54FF",
    "Name": "Property-Name-0102",
    "Address": "Property-Address-0102",
    "Description": "Property-Description-0102-Sample-Data",
    "SquareMeter": 192.25,
    "NumberRooms": 3,
    "NumberBathrooms": 1,
    "PropertyTypeId": "35E9F237-FB6E-4E8E-B2C5-B5255C24801F",
    "SalePrice": 250000.00,
    "RentPrice": 700.00,
    "SaleTax": 15.00,
    "IncomeTax": 10.00,
    "CodeInternal": "PCI0000102",
    "Year": 2011,
    "HasParking": true,
    "IsActive": true,
    "OwnerId": "A0FEA333-5986-42F8-8B3D-2EF65D85F1B8"
  },
  {
    "Id": "E0982F27-9737-4E9D-A694-EB436CCA9009",
    "Name": "Property-Name-0103",
    "Address": "Property-Address-0103",
    "Description": "Property-Description-0103-Sample-Data",
    "SquareMeter": 192.25,
    "NumberRooms": 3,
    "NumberBathrooms": 1,
    "PropertyTypeId": "7E8DFFC0-558E-4133-8386-DDB33B716AF4",
    "SalePrice": 250000.00,
    "RentPrice": 700.00,
    "SaleTax": 15.00,
    "IncomeTax": 10.00,
    "CodeInternal": "PCI0000103",
    "Year": 2010,
    "HasParking": true,
    "IsActive": true,
    "OwnerId": "8B7CECC3-E157-419A-AA14-99D5A3C934A0"
  },
  {
    "Id": "E7867344-B248-4F3B-B3B2-C6CB136A4D81",
    "Name": "Property-Name-0104",
    "Address": "Property-Address-0104",
    "Description": "Property-Description-0104-Sample-Data",
    "SquareMeter": 192.25,
    "NumberRooms": 3,
    "NumberBathrooms": 1,
    "PropertyTypeId": "16E5767E-F9D5-410B-B4AD-C9776E8712F2",
    "SalePrice": 250000.00,
    "RentPrice": 700.00,
    "SaleTax": 15.00,
    "IncomeTax": 10.00,
    "CodeInternal": "PCI0000104",
    "Year": 2013,
    "HasParking": false,
    "IsActive": true,
    "OwnerId": "A0FEA333-5986-42F8-8B3D-2EF65D85F1B8"
  },
  {
    "Id": "EC139F0E-5845-4E29-82B4-9C79514C6178",
    "Name": "Property-Name-0105",
    "Address": "Property-Address-0105",
    "Description": "Property-Description-0105-Sample-Data",
    "SquareMeter": 192.25,
    "NumberRooms": 3,
    "NumberBathrooms": 1,
    "PropertyTypeId": "4F426DDE-E40C-4819-97B5-AEF5F94A5D53",
    "SalePrice": 250000.00,
    "RentPrice": 700.00,
    "SaleTax": 15.00,
    "IncomeTax": 10.00,
    "CodeInternal": "PCI0000105",
    "Year": 2014,
    "HasParking": true,
    "IsActive": true,
    "OwnerId": "D0C11FF5-02AB-440A-966C-6AA5EDA9B2BB"
  },
  {
    "Id": "FDEF4925-88D9-4BEA-B9A9-B55868C2D870",
    "Name": "Property-Name-0106",
    "Address": "Property-Address-0106",
    "Description": "Property-Description-0106-Sample-Data",
    "SquareMeter": 192.25,
    "NumberRooms": 3,
    "NumberBathrooms": 1,
    "PropertyTypeId": "C82043A7-1C2A-46B7-A0BF-82CD04674EB2",
    "SalePrice": 250000.00,
    "RentPrice": 700.00,
    "SaleTax": 15.00,
    "IncomeTax": 10.00,
    "CodeInternal": "PCI0000106",
    "Year": 2013,
    "HasParking": false,
    "IsActive": true,
    "OwnerId": "D0C11FF5-02AB-440A-966C-6AA5EDA9B2BB"
  },
  {
    "Id": "9709E01C-DCD8-4BB8-8B76-0323BDDE3E04",
    "Name": "Property-Name-0107",
    "Address": "Property-Address-0107",
    "Description": "Property-Description-0107-Sample-Data",
    "SquareMeter": 192.25,
    "NumberRooms": 3,
    "NumberBathrooms": 1,
    "PropertyTypeId": "3CCA2E47-C344-4E6D-98C2-57FE35FC0F35",
    "SalePrice": 250000.00,
    "RentPrice": 700.00,
    "SaleTax": 15.00,
    "IncomeTax": 10.00,
    "CodeInternal": "PCI0000107",
    "Year": 2015,
    "HasParking": false,
    "IsActive": true,
    "OwnerId": "4FFCF2CC-9229-47B8-8F21-6654CDA47E2A"
  },
  {
    "Id": "AC4B8832-8627-4A6D-AC2C-75FDAB119B09",
    "Name": "Property-Name-0108",
    "Address": "Property-Address-0108",
    "Description": "Property-Description-0108-Sample-Data",
    "SquareMeter": 192.25,
    "NumberRooms": 3,
    "NumberBathrooms": 1,
    "PropertyTypeId": "2E191A01-5623-4C92-B9DF-811955F990E8",
    "SalePrice": 250000.00,
    "RentPrice": 700.00,
    "SaleTax": 15.00,
    "IncomeTax": 10.00,
    "CodeInternal": "PCI0000108",
    "Year": 2012,
    "HasParking": true,
    "IsActive": true,
    "OwnerId": "8B7CECC3-E157-419A-AA14-99D5A3C934A0"
  },
  {
    "Id": "F5319B62-DE67-44AA-BFD0-66F4AD194C0E",
    "Name": "Property-Name-0109",
    "Address": "Property-Address-0109",
    "Description": "Property-Description-0109-Sample-Data",
    "SquareMeter": 92.22,
    "NumberRooms": 3,
    "NumberBathrooms": 1,
    "PropertyTypeId": "69D3F1C8-0317-4332-9656-5F363960E210",
    "SalePrice": 250000.00,
    "RentPrice": 700.00,
    "SaleTax": 15.00,
    "IncomeTax": 10.00,
    "CodeInternal": "PCI0000109",
    "Year": 2013,
    "HasParking": true,
    "IsActive": true,
    "OwnerId": "0021CE10-1203-4459-A685-9F8698DA19CE"
  },
  {
    "Id": "4A49CECC-332D-4BF1-93A9-8B119041926E",
    "Name": "Property-Name-0110",
    "Address": "Property-Address-0110",
    "Description": "Property-Description-0110-Sample-Data",
    "SquareMeter": 88.51,
    "NumberRooms": 3,
    "NumberBathrooms": 1,
    "PropertyTypeId": "2E191A01-5623-4C92-B9DF-811955F990E8",
    "SalePrice": 250000.00,
    "RentPrice": 700.00,
    "SaleTax": 15.00,
    "IncomeTax": 10.00,
    "CodeInternal": "PCI0000110",
    "Year": 2016,
    "HasParking": true,
    "IsActive": true,
    "OwnerId": "E5C3D9B5-5988-48C6-96A3-02E680E48234"
  },
  {
    "Id": "3BFE3193-8C37-46E3-96AA-33BC87DEE695",
    "Name": "Property-Name-1001",
    "Address": "Property-Address-1001",
    "Description": "Property-Description-1001-Sample-Data",
    "SquareMeter": 192.25,
    "NumberRooms": 3,
    "NumberBathrooms": 1,
    "PropertyTypeId": "3CCA2E47-C344-4E6D-98C2-57FE35FC0F35",
    "SalePrice": 250000.00,
    "RentPrice": 700.00,
    "SaleTax": 15.00,
    "IncomeTax": 10.00,
    "CodeInternal": "PCI0001001",
    "Year": 2016,
    "HasParking": false,
    "IsActive": true,
    "OwnerId": "38440EEA-FC9F-4B6F-B623-F72FDDC66A29"
  },
  {
    "Id": "CAD17D0C-CAAE-4361-9CC9-7B406DF8387F",
    "Name": "Property-Name-1002",
    "Address": "Property-Address-1002",
    "Description": "Property-Description-1002-Sample-Data",
    "SquareMeter": 192.25,
    "NumberRooms": 3,
    "NumberBathrooms": 1,
    "PropertyTypeId": "C82043A7-1C2A-46B7-A0BF-82CD04674EB2",
    "SalePrice": 250000.00,
    "RentPrice": 700.00,
    "SaleTax": 15.00,
    "IncomeTax": 10.00,
    "CodeInternal": "PCI0001002",
    "Year": 2017,
    "HasParking": false,
    "IsActive": true,
    "OwnerId": "4FFCF2CC-9229-47B8-8F21-6654CDA47E2A"
  },
  {
    "Id": "1B656913-711C-4B7F-93CA-B090681228ED",
    "Name": "Property-Name-1003",
    "Address": "Property-Address-1003",
    "Description": "Property-Description-1003-Sample-Data",
    "SquareMeter": 192.25,
    "NumberRooms": 3,
    "NumberBathrooms": 1,
    "PropertyTypeId": "4F426DDE-E40C-4819-97B5-AEF5F94A5D53",
    "SalePrice": 250000.00,
    "RentPrice": 700.00,
    "SaleTax": 15.00,
    "IncomeTax": 10.00,
    "CodeInternal": "PCI0001003",
    "Year": 2019,
    "HasParking": true,
    "IsActive": true,
    "OwnerId": "41C43138-9280-4EDC-9307-BEBE359796A5"
  },
  {
    "Id": "96162BD0-E51F-4573-8B15-94201E691AB3",
    "Name": "Property-Name-1004",
    "Address": "Property-Address-1004",
    "Description": "Property-Description-1004-Sample-Data",
    "SquareMeter": 62.47,
    "NumberRooms": 3,
    "NumberBathrooms": 1,
    "PropertyTypeId": "69D3F1C8-0317-4332-9656-5F363960E210",
    "SalePrice": 250000.00,
    "RentPrice": 700.00,
    "SaleTax": 15.00,
    "IncomeTax": 10.00,
    "CodeInternal": "PCI0001004",
    "Year": 2016,
    "HasParking": false,
    "IsActive": true,
    "OwnerId": "38440EEA-FC9F-4B6F-B623-F72FDDC66A29"
  },
  {
    "Id": "0AE5ABAD-4A7A-4DA4-A049-56B0D3769548",
    "Name": "Property-Name-1005",
    "Address": "Property-Address-1005",
    "Description": "Property-Description-1005-Sample-Data",
    "SquareMeter": 192.25,
    "NumberRooms": 3,
    "NumberBathrooms": 1,
    "PropertyTypeId": "16E5767E-F9D5-410B-B4AD-C9776E8712F2",
    "SalePrice": 250000.00,
    "RentPrice": 700.00,
    "SaleTax": 15.00,
    "IncomeTax": 10.00,
    "CodeInternal": "PCI0001005",
    "Year": 2019,
    "HasParking": false,
    "IsActive": true,
    "OwnerId": "41C43138-9280-4EDC-9307-BEBE359796A5"
  },
  {
    "Id": "3B5BB926-2E53-4F9C-AD5E-11FA08E65547",
    "Name": "Property-Name-1006",
    "Address": "Property-Address-1006",
    "Description": "Property-Description-1006-Sample-Data",
    "SquareMeter": 192.25,
    "NumberRooms": 3,
    "NumberBathrooms": 1,
    "PropertyTypeId": "7E8DFFC0-558E-4133-8386-DDB33B716AF4",
    "SalePrice": 250000.00,
    "RentPrice": 700.00,
    "SaleTax": 15.00,
    "IncomeTax": 10.00,
    "CodeInternal": "PCI0001006",
    "Year": 2017,
    "HasParking": true,
    "IsActive": true,
    "OwnerId": "4FFCF2CC-9229-47B8-8F21-6654CDA47E2A"
  },
  {
    "Id": "17BD3DA8-DCA2-4B11-B73A-5F47A825E267",
    "Name": "Property-Name-1008",
    "Address": "Property-Address-1008",
    "Description": "Property-Description-1008-Sample-Data",
    "SquareMeter": 192.25,
    "NumberRooms": 3,
    "NumberBathrooms": 1,
    "PropertyTypeId": "35E9F237-FB6E-4E8E-B2C5-B5255C24801F",
    "SalePrice": 250000.00,
    "RentPrice": 700.00,
    "SaleTax": 15.00,
    "IncomeTax": 10.00,
    "CodeInternal": "PCI0001008",
    "Year": 2018,
    "HasParking": true,
    "IsActive": true,
    "OwnerId": "41C43138-9280-4EDC-9307-BEBE359796A5"
  },
  {
    "Id": "7CBC41ED-D4BE-492D-97CC-C89BCF1E2BF8",
    "Name": "Property-Name-1009",
    "Address": "Property-Address-1009",
    "Description": "Property-Description-1009-Sample-Data",
    "SquareMeter": 192.25,
    "NumberRooms": 3,
    "NumberBathrooms": 1,
    "PropertyTypeId": "4F426DDE-E40C-4819-97B5-AEF5F94A5D53",
    "SalePrice": 250000.00,
    "RentPrice": 700.00,
    "SaleTax": 15.00,
    "IncomeTax": 10.00,
    "CodeInternal": "PCI0001009",
    "Year": 2015,
    "HasParking": true,
    "IsActive": true,
    "OwnerId": "38440EEA-FC9F-4B6F-B623-F72FDDC66A29"
  },
  {
    "Id": "ED12A472-D3D9-4122-A197-AD6CDF0108AF",
    "Name": "Property-Name-1010",
    "Address": "Property-Address-1010",
    "Description": "Property-Description-1010-Sample-Data",
    "SquareMeter": 192.25,
    "NumberRooms": 3,
    "NumberBathrooms": 1,
    "PropertyTypeId": "92E2453A-7D2F-44A4-A9FB-3E11ED3BB458",
    "SalePrice": 250000.00,
    "RentPrice": 700.00,
    "SaleTax": 15.00,
    "IncomeTax": 10.00,
    "CodeInternal": "PCI0001010",
    "Year": 2020,
    "HasParking": true,
    "IsActive": true,
    "OwnerId": "4FFCF2CC-9229-47B8-8F21-6654CDA47E2A"
  },
  {
    "Id": "418A1C6C-834F-4308-853B-1AA5639663F4",
    "Name": "Property-Name-10001",
    "Address": "Property-Address-10001",
    "Description": "Property-Description-10001-Sample-Data",
    "SquareMeter": 192.25,
    "NumberRooms": 3,
    "NumberBathrooms": 1,
    "PropertyTypeId": "2E191A01-5623-4C92-B9DF-811955F990E8",
    "SalePrice": 250000.00,
    "RentPrice": 700.00,
    "SaleTax": 15.00,
    "IncomeTax": 10.00,
    "CodeInternal": "PCI0010001",
    "Year": 2014,
    "HasParking": true,
    "IsActive": true,
    "OwnerId": "8B7CECC3-E157-419A-AA14-99D5A3C934A0"
  },
  {
    "Id": "05605ECD-7170-42EE-B276-286326ED093A",
    "Name": "Property-Name-10002",
    "Address": "Property-Address-10002",
    "Description": "Property-Description-10002-Sample-Data",
    "SquareMeter": 241.21,
    "NumberRooms": 3,
    "NumberBathrooms": 1,
    "PropertyTypeId": "69D3F1C8-0317-4332-9656-5F363960E210",
    "SalePrice": 250000.00,
    "RentPrice": 700.00,
    "SaleTax": 15.00,
    "IncomeTax": 10.00,
    "CodeInternal": "PCI0010002",
    "Year": 2015,
    "HasParking": true,
    "IsActive": true,
    "OwnerId": "D0C11FF5-02AB-440A-966C-6AA5EDA9B2BB"
  },
  {
    "Id": "69D026E3-C5B7-4F7B-8172-8A555844CF1E",
    "Name": "Property-Name-10004",
    "Address": "Property-Address-10004",
    "Description": "Property-Description-10004-Sample-Data",
    "SquareMeter": 192.25,
    "NumberRooms": 3,
    "NumberBathrooms": 1,
    "PropertyTypeId": "2E191A01-5623-4C92-B9DF-811955F990E8",
    "SalePrice": 250000.00,
    "RentPrice": 700.00,
    "SaleTax": 15.00,
    "IncomeTax": 10.00,
    "CodeInternal": "PCI0010004",
    "Year": 2012,
    "HasParking": true,
    "IsActive": true,
    "OwnerId": "4FFCF2CC-9229-47B8-8F21-6654CDA47E2A"
  },
  {
    "Id": "C9AB8CE9-E2CF-42DC-813C-911800972427",
    "Name": "Property-Name-10005",
    "Address": "Property-Address-10005",
    "Description": "Property-Description-10005-Sample-Data",
    "SquareMeter": 192.25,
    "NumberRooms": 3,
    "NumberBathrooms": 1,
    "PropertyTypeId": "C82043A7-1C2A-46B7-A0BF-82CD04674EB2",
    "SalePrice": 250000.00,
    "RentPrice": 700.00,
    "SaleTax": 15.00,
    "IncomeTax": 10.00,
    "CodeInternal": "PCI0010005",
    "Year": 2013,
    "HasParking": false,
    "IsActive": true,
    "OwnerId": "38440EEA-FC9F-4B6F-B623-F72FDDC66A29"
  },
  {
    "Id": "F165E43D-4F1B-40D5-9AD3-F2DA65A19582",
    "Name": "Property-Name-10006",
    "Address": "Property-Address-10006",
    "Description": "Property-Description-10006-Sample-Data",
    "SquareMeter": 192.25,
    "NumberRooms": 3,
    "NumberBathrooms": 1,
    "PropertyTypeId": "F4E25DF1-82C4-4685-91AC-7305F6EB9ADD",
    "SalePrice": 250000.00,
    "RentPrice": 700.00,
    "SaleTax": 15.00,
    "IncomeTax": 10.00,
    "CodeInternal": "PCI0010006",
    "Year": 2014,
    "HasParking": false,
    "IsActive": true,
    "OwnerId": "0021CE10-1203-4459-A685-9F8698DA19CE"
  },
  {
    "Id": "49012F7A-A21F-4E05-9A97-FE6CA92D780B",
    "Name": "Property-Name-10007",
    "Address": "Property-Address-10007",
    "Description": "Property-Description-10007-Sample-Data",
    "SquareMeter": 192.25,
    "NumberRooms": 3,
    "NumberBathrooms": 1,
    "PropertyTypeId": "35E9F237-FB6E-4E8E-B2C5-B5255C24801F",
    "SalePrice": 250000.00,
    "RentPrice": 700.00,
    "SaleTax": 15.00,
    "IncomeTax": 10.00,
    "CodeInternal": "PCI0010007",
    "Year": 2015,
    "HasParking": true,
    "IsActive": true,
    "OwnerId": "0C3A18AC-068D-41C2-BA37-4CA1BCD6F9F7"
  },
  {
    "Id": "BEA8FBA5-0FC0-4948-9FBE-AF39DC7EC0BB",
    "Name": "Property-Name-10009",
    "Address": "Property-Address-10009",
    "Description": "Property-Description-10009-Sample-Data",
    "SquareMeter": 192.25,
    "NumberRooms": 3,
    "NumberBathrooms": 1,
    "PropertyTypeId": "C82043A7-1C2A-46B7-A0BF-82CD04674EB2",
    "SalePrice": 250000.00,
    "RentPrice": 700.00,
    "SaleTax": 15.00,
    "IncomeTax": 10.00,
    "CodeInternal": "PCI0010009",
    "Year": 2017,
    "HasParking": false,
    "IsActive": true,
    "OwnerId": "4FFCF2CC-9229-47B8-8F21-6654CDA47E2A"
  },
  {
    "Id": "B046A7B3-A70E-4228-9DA1-653598539EED",
    "Name": "Property-Name-10010",
    "Address": "Property-Address-10010",
    "Description": "Property-Description-10010-Sample-Data",
    "SquareMeter": 192.25,
    "NumberRooms": 3,
    "NumberBathrooms": 1,
    "PropertyTypeId": "4F426DDE-E40C-4819-97B5-AEF5F94A5D53",
    "SalePrice": 250000.00,
    "RentPrice": 700.00,
    "SaleTax": 15.00,
    "IncomeTax": 10.00,
    "CodeInternal": "PCI0010010",
    "Year": 2019,
    "HasParking": true,
    "IsActive": true,
    "OwnerId": "8B7CECC3-E157-419A-AA14-99D5A3C934A0"
  },
  {
    "Id": "4C07847D-02B8-4AED-A230-9A86791C2E7B",
    "Name": "Property-Name-0201",
    "Address": "Property-Address-0201",
    "Description": "Property-Description-0201-Sample-Data",
    "SquareMeter": 192.25,
    "NumberRooms": 3,
    "NumberBathrooms": 1,
    "PropertyTypeId": "4F426DDE-E40C-4819-97B5-AEF5F94A5D53",
    "SalePrice": 250000.00,
    "RentPrice": 700.00,
    "SaleTax": 15.00,
    "IncomeTax": 10.00,
    "CodeInternal": "PCI0000201",
    "Year": 2020,
    "HasParking": true,
    "IsActive": true,
    "OwnerId": "D0C11FF5-02AB-440A-966C-6AA5EDA9B2BB"
  },
  {
    "Id": "0C2D8FB0-1DAA-4267-99F2-DFAEF39FD1C1",
    "Name": "Property-Name-0202",
    "Address": "Property-Address-0202",
    "Description": "Property-Description-0202-Sample-Data",
    "SquareMeter": 192.25,
    "NumberRooms": 3,
    "NumberBathrooms": 1,
    "PropertyTypeId": "35E9F237-FB6E-4E8E-B2C5-B5255C24801F",
    "SalePrice": 250000.00,
    "RentPrice": 700.00,
    "SaleTax": 15.00,
    "IncomeTax": 10.00,
    "CodeInternal": "PCI0000202",
    "Year": 2011,
    "HasParking": true,
    "IsActive": true,
    "OwnerId": "0C3A18AC-068D-41C2-BA37-4CA1BCD6F9F7"
  },
  {
    "Id": "A968C874-CD42-45ED-8B71-4DBF3B714648",
    "Name": "Property-Name-0203",
    "Address": "Property-Address-0203",
    "Description": "Property-Description-0203-Sample-Data",
    "SquareMeter": 192.25,
    "NumberRooms": 3,
    "NumberBathrooms": 1,
    "PropertyTypeId": "7E8DFFC0-558E-4133-8386-DDB33B716AF4",
    "SalePrice": 250000.00,
    "RentPrice": 700.00,
    "SaleTax": 15.00,
    "IncomeTax": 10.00,
    "CodeInternal": "PCI0000203",
    "Year": 2010,
    "HasParking": true,
    "IsActive": true,
    "OwnerId": "38440EEA-FC9F-4B6F-B623-F72FDDC66A29"
  },
  {
    "Id": "6913E020-858B-4C67-9DFB-C726544E7D2E",
    "Name": "Property-Name-0204",
    "Address": "Property-Address-0204",
    "Description": "Property-Description-0204-Sample-Data",
    "SquareMeter": 192.25,
    "NumberRooms": 3,
    "NumberBathrooms": 1,
    "PropertyTypeId": "92E2453A-7D2F-44A4-A9FB-3E11ED3BB458",
    "SalePrice": 250000.00,
    "RentPrice": 700.00,
    "SaleTax": 15.00,
    "IncomeTax": 10.00,
    "CodeInternal": "PCI0000204",
    "Year": 2012,
    "HasParking": true,
    "IsActive": true,
    "OwnerId": "A0FEA333-5986-42F8-8B3D-2EF65D85F1B8"
  },
  {
    "Id": "C158B104-D908-4CC5-95DF-46CDB0709A7D",
    "Name": "Property-Name-0206",
    "Address": "Property-Address-0206",
    "Description": "Property-Description-0206-Sample-Data",
    "SquareMeter": 192.25,
    "NumberRooms": 3,
    "NumberBathrooms": 1,
    "PropertyTypeId": "F4E25DF1-82C4-4685-91AC-7305F6EB9ADD",
    "SalePrice": 250000.00,
    "RentPrice": 700.00,
    "SaleTax": 15.00,
    "IncomeTax": 10.00,
    "CodeInternal": "PCI0000206",
    "Year": 2014,
    "HasParking": false,
    "IsActive": true,
    "OwnerId": "0C3A18AC-068D-41C2-BA37-4CA1BCD6F9F7"
  },
  {
    "Id": "0986034D-0886-49BB-9078-B8D60EBE12FA",
    "Name": "Property-Name-0207",
    "Address": "Property-Address-0207",
    "Description": "Property-Description-0207-Sample-Data",
    "SquareMeter": 192.25,
    "NumberRooms": 3,
    "NumberBathrooms": 1,
    "PropertyTypeId": "3CCA2E47-C344-4E6D-98C2-57FE35FC0F35",
    "SalePrice": 250000.00,
    "RentPrice": 700.00,
    "SaleTax": 15.00,
    "IncomeTax": 10.00,
    "CodeInternal": "PCI0000207",
    "Year": 2013,
    "HasParking": false,
    "IsActive": true,
    "OwnerId": "D0C11FF5-02AB-440A-966C-6AA5EDA9B2BB"
  },
  {
    "Id": "E63E0DB0-45AA-49AF-A7E4-02203E1463EE",
    "Name": "Property-Name-0208",
    "Address": "Property-Address-0208",
    "Description": "Property-Description-0208-Sample-Data",
    "SquareMeter": 192.25,
    "NumberRooms": 3,
    "NumberBathrooms": 1,
    "PropertyTypeId": "92E2453A-7D2F-44A4-A9FB-3E11ED3BB458",
    "SalePrice": 250000.00,
    "RentPrice": 700.00,
    "SaleTax": 15.00,
    "IncomeTax": 10.00,
    "CodeInternal": "PCI0000208",
    "Year": 2012,
    "HasParking": true,
    "IsActive": true,
    "OwnerId": "A0FEA333-5986-42F8-8B3D-2EF65D85F1B8"
  },
  {
    "Id": "88C0C26A-1754-4B88-A807-777B805B5C0F",
    "Name": "Property-Name-0209",
    "Address": "Property-Address-0209",
    "Description": "Property-Description-0209-Sample-Data",
    "SquareMeter": 192.25,
    "NumberRooms": 3,
    "NumberBathrooms": 1,
    "PropertyTypeId": "7E8DFFC0-558E-4133-8386-DDB33B716AF4",
    "SalePrice": 250000.00,
    "RentPrice": 700.00,
    "SaleTax": 15.00,
    "IncomeTax": 10.00,
    "CodeInternal": "PCI0000209",
    "Year": 2015,
    "HasParking": true,
    "IsActive": true,
    "OwnerId": "0C3A18AC-068D-41C2-BA37-4CA1BCD6F9F7"
  },
  {
    "Id": "B34C2CE8-D8D2-4670-AA15-3558B07976FE",
    "Name": "Property-Name-0210",
    "Address": "Property-Address-0210",
    "Description": "Property-Description-0210-Sample-Data",
    "SquareMeter": 192.25,
    "NumberRooms": 3,
    "NumberBathrooms": 1,
    "PropertyTypeId": "C82043A7-1C2A-46B7-A0BF-82CD04674EB2",
    "SalePrice": 250000.00,
    "RentPrice": 700.00,
    "SaleTax": 15.00,
    "IncomeTax": 10.00,
    "CodeInternal": "PCI0000210",
    "Year": 2011,
    "HasParking": false,
    "IsActive": true,
    "OwnerId": "38440EEA-FC9F-4B6F-B623-F72FDDC66A29"
  },
  {
    "Id": "CABD5DD4-DAD2-4195-B6CB-BE1071DFD35F",
    "Name": "Property-Name-0501",
    "Address": "Property-Address-0501",
    "Description": "Property-Description-0501-Sample-Data",
    "SquareMeter": 192.25,
    "NumberRooms": 3,
    "NumberBathrooms": 1,
    "PropertyTypeId": "35E9F237-FB6E-4E8E-B2C5-B5255C24801F",
    "SalePrice": 250000.00,
    "RentPrice": 700.00,
    "SaleTax": 15.00,
    "IncomeTax": 10.00,
    "CodeInternal": "PCI0000501",
    "Year": 2020,
    "HasParking": true,
    "IsActive": true,
    "OwnerId": "A0FEA333-5986-42F8-8B3D-2EF65D85F1B8"
  },
  {
    "Id": "CADFF92C-8D80-4F2D-912D-CC28A1175C14",
    "Name": "Property-Name-0502",
    "Address": "Property-Address-0502",
    "Description": "Property-Description-0502-Sample-Data",
    "SquareMeter": 192.25,
    "NumberRooms": 3,
    "NumberBathrooms": 1,
    "PropertyTypeId": "35E9F237-FB6E-4E8E-B2C5-B5255C24801F",
    "SalePrice": 250000.00,
    "RentPrice": 700.00,
    "SaleTax": 15.00,
    "IncomeTax": 10.00,
    "CodeInternal": "PCI0000502",
    "Year": 2020,
    "HasParking": true,
    "IsActive": true,
    "OwnerId": "6449C449-59DA-4C60-9AB2-1B9949024C86"
  },
  {
    "Id": "ED0A298B-1485-4116-9D40-F127A3B7F27C",
    "Name": "Property-Name-0503",
    "Address": "Property-Address-0503",
    "Description": "Property-Description-0503-Sample-Data",
    "SquareMeter": 192.25,
    "NumberRooms": 3,
    "NumberBathrooms": 1,
    "PropertyTypeId": "16E5767E-F9D5-410B-B4AD-C9776E8712F2",
    "SalePrice": 250000.00,
    "RentPrice": 700.00,
    "SaleTax": 15.00,
    "IncomeTax": 10.00,
    "CodeInternal": "PCI0000503",
    "Year": 2020,
    "HasParking": false,
    "IsActive": true,
    "OwnerId": "38440EEA-FC9F-4B6F-B623-F72FDDC66A29"
  },
  {
    "Id": "5F0B6538-AC9C-4B13-84C7-5058380821CC",
    "Name": "Property-Name-0504",
    "Address": "Property-Address-0504",
    "Description": "Property-Description-0504-Sample-Data",
    "SquareMeter": 192.25,
    "NumberRooms": 3,
    "NumberBathrooms": 1,
    "PropertyTypeId": "7E8DFFC0-558E-4133-8386-DDB33B716AF4",
    "SalePrice": 250000.00,
    "RentPrice": 700.00,
    "SaleTax": 15.00,
    "IncomeTax": 10.00,
    "CodeInternal": "PCI0000504",
    "Year": 2020,
    "HasParking": true,
    "IsActive": true,
    "OwnerId": "0021CE10-1203-4459-A685-9F8698DA19CE"
  },
  {
    "Id": "1F7DF5A5-2FA9-400F-8B5B-D3D8A7CDD68E",
    "Name": "Property-Name-0505",
    "Address": "Property-Address-0505",
    "Description": "Property-Description-0505-Sample-Data",
    "SquareMeter": 192.25,
    "NumberRooms": 3,
    "NumberBathrooms": 1,
    "PropertyTypeId": "F4E25DF1-82C4-4685-91AC-7305F6EB9ADD",
    "SalePrice": 250000.00,
    "RentPrice": 700.00,
    "SaleTax": 15.00,
    "IncomeTax": 10.00,
    "CodeInternal": "PCI0000505",
    "Year": 2020,
    "HasParking": false,
    "IsActive": true,
    "OwnerId": "6449C449-59DA-4C60-9AB2-1B9949024C86"
  },
  {
    "Id": "134CD482-7C1E-4493-93E5-3DD624B343C9",
    "Name": "Property-Name-7002",
    "Address": "Property-Address-7002",
    "Description": "Property-Description-7002-Sample-Data",
    "SquareMeter": 192.25,
    "NumberRooms": 3,
    "NumberBathrooms": 1,
    "PropertyTypeId": "35E9F237-FB6E-4E8E-B2C5-B5255C24801F",
    "SalePrice": 250000.00,
    "RentPrice": 700.00,
    "SaleTax": 15.00,
    "IncomeTax": 10.00,
    "CodeInternal": "PCI0007002",
    "Year": 2021,
    "HasParking": true,
    "IsActive": true,
    "OwnerId": "0021CE10-1203-4459-A685-9F8698DA19CE"
  },
  {
    "Id": "91984212-F153-422D-B675-73900D5CC317",
    "Name": "Property-Name-7003",
    "Address": "Property-Address-7003",
    "Description": "Property-Description-7003-Sample-Data",
    "SquareMeter": 192.25,
    "NumberRooms": 3,
    "NumberBathrooms": 1,
    "PropertyTypeId": "3CCA2E47-C344-4E6D-98C2-57FE35FC0F35",
    "SalePrice": 250000.00,
    "RentPrice": 700.00,
    "SaleTax": 15.00,
    "IncomeTax": 10.00,
    "CodeInternal": "PCI0007003",
    "Year": 2021,
    "HasParking": false,
    "IsActive": true,
    "OwnerId": "D0C11FF5-02AB-440A-966C-6AA5EDA9B2BB"
  },
  {
    "Id": "820CE4D9-58A4-4711-B08B-751E619AC24F",
    "Name": "Property-Name-7004",
    "Address": "Property-Address-7004",
    "Description": "Property-Description-7004-Sample-Data",
    "SquareMeter": 250.66,
    "NumberRooms": 3,
    "NumberBathrooms": 1,
    "PropertyTypeId": "69D3F1C8-0317-4332-9656-5F363960E210",
    "SalePrice": 250000.00,
    "RentPrice": 700.00,
    "SaleTax": 15.00,
    "IncomeTax": 10.00,
    "CodeInternal": "PCI0007004",
    "Year": 2021,
    "HasParking": true,
    "IsActive": true,
    "OwnerId": "38440EEA-FC9F-4B6F-B623-F72FDDC66A29"
  },
  {
    "Id": "EA813E92-FDF7-4BE9-A740-1ADD3CF43C68",
    "Name": "Property-Name-7005",
    "Address": "Property-Address-7005",
    "Description": "Property-Description-7005-Sample-Data",
    "SquareMeter": 192.25,
    "NumberRooms": 3,
    "NumberBathrooms": 1,
    "PropertyTypeId": "92E2453A-7D2F-44A4-A9FB-3E11ED3BB458",
    "SalePrice": 250000.00,
    "RentPrice": 700.00,
    "SaleTax": 15.00,
    "IncomeTax": 10.00,
    "CodeInternal": "PCI0007005",
    "Year": 2021,
    "HasParking": true,
    "IsActive": true,
    "OwnerId": "0021CE10-1203-4459-A685-9F8698DA19CE"
  },
  {
    "Id": "BE868C62-2939-4A0F-8980-4201937E3659",
    "Name": "Property-Name-0912",
    "Address": "Property-Address-0912",
    "Description": "Property-Description-0912-Sample-Data",
    "SquareMeter": 192.25,
    "NumberRooms": 3,
    "NumberBathrooms": 1,
    "PropertyTypeId": "3CCA2E47-C344-4E6D-98C2-57FE35FC0F35",
    "SalePrice": 250000.00,
    "RentPrice": 700.00,
    "SaleTax": 15.00,
    "IncomeTax": 10.00,
    "CodeInternal": "PCI0000912",
    "Year": 2016,
    "HasParking": false,
    "IsActive": true,
    "OwnerId": "D0C11FF5-02AB-440A-966C-6AA5EDA9B2BB"
  },
  {
    "Id": "D80D759D-AB99-4726-BCB9-88DBCEA4CB3A",
    "Name": "Property-Name-0913",
    "Address": "Property-Address-0913",
    "Description": "Property-Description-0913-Sample-Data",
    "SquareMeter": 192.25,
    "NumberRooms": 3,
    "NumberBathrooms": 1,
    "PropertyTypeId": "3CCA2E47-C344-4E6D-98C2-57FE35FC0F35",
    "SalePrice": 250000.00,
    "RentPrice": 700.00,
    "SaleTax": 15.00,
    "IncomeTax": 10.00,
    "CodeInternal": "PCI0000913",
    "Year": 2018,
    "HasParking": false,
    "IsActive": true,
    "OwnerId": "8B7CECC3-E157-419A-AA14-99D5A3C934A0"
  },
  {
    "Id": "DEED106C-B3BB-4110-BA92-86B0CE5707C8",
    "Name": "Property-Name-0916",
    "Address": "Property-Address-0916",
    "Description": "Property-Description-0916-Sample-Data",
    "SquareMeter": 192.25,
    "NumberRooms": 3,
    "NumberBathrooms": 1,
    "PropertyTypeId": "C82043A7-1C2A-46B7-A0BF-82CD04674EB2",
    "SalePrice": 250000.00,
    "RentPrice": 700.00,
    "SaleTax": 15.00,
    "IncomeTax": 10.00,
    "CodeInternal": "PCI0000916",
    "Year": 2014,
    "HasParking": false,
    "IsActive": true,
    "OwnerId": "D0C11FF5-02AB-440A-966C-6AA5EDA9B2BB"
  },
  {
    "Id": "04C170C3-27BF-4F34-A052-16297E763C54",
    "Name": "Property-Name-0917",
    "Address": "Property-Address-0917",
    "Description": "Property-Description-0917-Sample-Data",
    "SquareMeter": 192.25,
    "NumberRooms": 3,
    "NumberBathrooms": 1,
    "PropertyTypeId": "4F426DDE-E40C-4819-97B5-AEF5F94A5D53",
    "SalePrice": 250000.00,
    "RentPrice": 700.00,
    "SaleTax": 15.00,
    "IncomeTax": 10.00,
    "CodeInternal": "PCI0000917",
    "Year": 2018,
    "HasParking": true,
    "IsActive": true,
    "OwnerId": "8B7CECC3-E157-419A-AA14-99D5A3C934A0"
  },
  {
    "Id": "853AA201-6C32-4D96-91A4-561600DDC536",
    "Name": "Property-Name-0918",
    "Address": "Property-Address-0918",
    "Description": "Property-Description-0918-Sample-Data",
    "SquareMeter": 192.25,
    "NumberRooms": 3,
    "NumberBathrooms": 1,
    "PropertyTypeId": "3CCA2E47-C344-4E6D-98C2-57FE35FC0F35",
    "SalePrice": 250000.00,
    "RentPrice": 700.00,
    "SaleTax": 15.00,
    "IncomeTax": 10.00,
    "CodeInternal": "PCI0000918",
    "Year": 2005,
    "HasParking": false,
    "IsActive": true,
    "OwnerId": "D0C11FF5-02AB-440A-966C-6AA5EDA9B2BB"
  },
  {
    "Id": "57BCF8E4-1838-427B-A0CE-333A0756AC51",
    "Name": "Property-Name-0052",
    "Address": "Property-Address-0052",
    "Description": "Property-Description-0052-Sample-Data",
    "SquareMeter": 145.15,
    "NumberRooms": 3,
    "NumberBathrooms": 1,
    "PropertyTypeId": "69D3F1C8-0317-4332-9656-5F363960E210",
    "SalePrice": 250000.00,
    "RentPrice": 700.00,
    "SaleTax": 15.00,
    "IncomeTax": 10.00,
    "CodeInternal": "PCI0000052",
    "Year": 2002,
    "HasParking": false,
    "IsActive": true,
    "OwnerId": "8B7CECC3-E157-419A-AA14-99D5A3C934A0"
  },
  {
    "Id": "66E075F2-5B01-4B9A-8439-0C27FC938796",
    "Name": "Property-Name-0053",
    "Address": "Property-Address-0053",
    "Description": "Property-Description-0053-Sample-Data",
    "SquareMeter": 192.25,
    "NumberRooms": 3,
    "NumberBathrooms": 1,
    "PropertyTypeId": "7E8DFFC0-558E-4133-8386-DDB33B716AF4",
    "SalePrice": 250000.00,
    "RentPrice": 700.00,
    "SaleTax": 15.00,
    "IncomeTax": 10.00,
    "CodeInternal": "PCI0000053",
    "Year": 2003,
    "HasParking": true,
    "IsActive": true,
    "OwnerId": "A0FEA333-5986-42F8-8B3D-2EF65D85F1B8"
  },
  {
    "Id": "C81F06A6-2D04-4487-A6E6-614211DB2159",
    "Name": "Property-Name-0054",
    "Address": "Property-Address-0054",
    "Description": "Property-Description-0054-Sample-Data",
    "SquareMeter": 192.25,
    "NumberRooms": 3,
    "NumberBathrooms": 1,
    "PropertyTypeId": "92E2453A-7D2F-44A4-A9FB-3E11ED3BB458",
    "SalePrice": 250000.00,
    "RentPrice": 700.00,
    "SaleTax": 15.00,
    "IncomeTax": 10.00,
    "CodeInternal": "PCI0000054",
    "Year": 2001,
    "HasParking": true,
    "IsActive": true,
    "OwnerId": "A0FEA333-5986-42F8-8B3D-2EF65D85F1B8"
  },
  {
    "Id": "84431CBE-7C09-46E1-A9AB-06EC516710A4",
    "Name": "Property-Name-0055",
    "Address": "Property-Address-0055",
    "Description": "Property-Description-0055-Sample-Data",
    "SquareMeter": 192.25,
    "NumberRooms": 3,
    "NumberBathrooms": 1,
    "PropertyTypeId": "4F426DDE-E40C-4819-97B5-AEF5F94A5D53",
    "SalePrice": 250000.00,
    "RentPrice": 700.00,
    "SaleTax": 15.00,
    "IncomeTax": 10.00,
    "CodeInternal": "PCI0000055",
    "Year": 2008,
    "HasParking": true,
    "IsActive": true,
    "OwnerId": "38440EEA-FC9F-4B6F-B623-F72FDDC66A29"
  },
  {
    "Id": "01FB22C2-F16F-4C7E-BF91-BFFCC8062B13",
    "Name": "Property-Name-0056",
    "Address": "Property-Address-0056",
    "Description": "Property-Description-0056-Sample-Data",
    "SquareMeter": 192.25,
    "NumberRooms": 3,
    "NumberBathrooms": 1,
    "PropertyTypeId": "C82043A7-1C2A-46B7-A0BF-82CD04674EB2",
    "SalePrice": 250000.00,
    "RentPrice": 700.00,
    "SaleTax": 15.00,
    "IncomeTax": 10.00,
    "CodeInternal": "PCI0000056",
    "Year": 2006,
    "HasParking": false,
    "IsActive": true,
    "OwnerId": "D0C11FF5-02AB-440A-966C-6AA5EDA9B2BB"
  },
  {
    "Id": "1F8BCCCF-A4CD-45BE-9C41-78244D470090",
    "Name": "Property-Name-0057",
    "Address": "Property-Address-0057",
    "Description": "Property-Description-0057-Sample-Data",
    "SquareMeter": 192.25,
    "NumberRooms": 3,
    "NumberBathrooms": 1,
    "PropertyTypeId": "16E5767E-F9D5-410B-B4AD-C9776E8712F2",
    "SalePrice": 250000.00,
    "RentPrice": 700.00,
    "SaleTax": 15.00,
    "IncomeTax": 10.00,
    "CodeInternal": "PCI0000057",
    "Year": 2009,
    "HasParking": false,
    "IsActive": true,
    "OwnerId": "6449C449-59DA-4C60-9AB2-1B9949024C86"
  },
  {
    "Id": "DFA88D7C-B05A-4075-8D84-3C29ACD38DC6",
    "Name": "Property-Name-0059",
    "Address": "Property-Address-0059",
    "Description": "Property-Description-0059-Sample-Data",
    "SquareMeter": 192.25,
    "NumberRooms": 3,
    "NumberBathrooms": 1,
    "PropertyTypeId": "4F426DDE-E40C-4819-97B5-AEF5F94A5D53",
    "SalePrice": 250000.00,
    "RentPrice": 700.00,
    "SaleTax": 15.00,
    "IncomeTax": 10.00,
    "CodeInternal": "PCI0000059",
    "Year": 2003,
    "HasParking": true,
    "IsActive": true,
    "OwnerId": "38440EEA-FC9F-4B6F-B623-F72FDDC66A29"
  },
  {
    "Id": "67DDF037-40FF-423C-A7E3-163C50222BF4",
    "Name": "Property-Name-3001",
    "Address": "Property-Address-3001",
    "Description": "Property-Description-3001-Sample-Data",
    "SquareMeter": 192.25,
    "NumberRooms": 3,
    "NumberBathrooms": 1,
    "PropertyTypeId": "2E191A01-5623-4C92-B9DF-811955F990E8",
    "SalePrice": 250000.00,
    "RentPrice": 700.00,
    "SaleTax": 15.00,
    "IncomeTax": 10.00,
    "CodeInternal": "PCI0003001",
    "Year": 2018,
    "HasParking": true,
    "IsActive": true,
    "OwnerId": "D0C11FF5-02AB-440A-966C-6AA5EDA9B2BB"
  },
  {
    "Id": "4F208DDD-0437-458B-84B7-5AC6FF698B52",
    "Name": "Property-Name-3002",
    "Address": "Property-Address-3002",
    "Description": "Property-Description-3002-Sample-Data",
    "SquareMeter": 192.25,
    "NumberRooms": 3,
    "NumberBathrooms": 1,
    "PropertyTypeId": "C82043A7-1C2A-46B7-A0BF-82CD04674EB2",
    "SalePrice": 250000.00,
    "RentPrice": 700.00,
    "SaleTax": 15.00,
    "IncomeTax": 10.00,
    "CodeInternal": "PCI0003002",
    "Year": 2015,
    "HasParking": false,
    "IsActive": true,
    "OwnerId": "8B7CECC3-E157-419A-AA14-99D5A3C934A0"
  },
  {
    "Id": "8A8EC6AE-0705-4425-B3CE-FC576EAE4B27",
    "Name": "Property-Name-3003",
    "Address": "Property-Address-3003",
    "Description": "Property-Description-3003-Sample-Data",
    "SquareMeter": 192.25,
    "NumberRooms": 3,
    "NumberBathrooms": 1,
    "PropertyTypeId": "3CCA2E47-C344-4E6D-98C2-57FE35FC0F35",
    "SalePrice": 250000.00,
    "RentPrice": 700.00,
    "SaleTax": 15.00,
    "IncomeTax": 10.00,
    "CodeInternal": "PCI00003003",
    "Year": 2013,
    "HasParking": false,
    "IsActive": true,
    "OwnerId": "D0C11FF5-02AB-440A-966C-6AA5EDA9B2BB"
  },
  {
    "Id": "8670E070-700C-42E8-A77F-5B6259B4C431",
    "Name": "Property-Name-3004",
    "Address": "Property-Address-3004",
    "Description": "Property-Description-3004-Sample-Data",
    "SquareMeter": 192.25,
    "NumberRooms": 3,
    "NumberBathrooms": 1,
    "PropertyTypeId": "7E8DFFC0-558E-4133-8386-DDB33B716AF4",
    "SalePrice": 250000.00,
    "RentPrice": 700.00,
    "SaleTax": 15.00,
    "IncomeTax": 10.00,
    "CodeInternal": "PCI0003004",
    "Year": 2019,
    "HasParking": true,
    "IsActive": true,
    "OwnerId": "6449C449-59DA-4C60-9AB2-1B9949024C86"
  },
  {
    "Id": "39BD5372-AFD6-48D2-8A27-80A527853DD7",
    "Name": "Property-Name-3005",
    "Address": "Property-Address-3005",
    "Description": "Property-Description-3005-Sample-Data",
    "SquareMeter": 192.25,
    "NumberRooms": 3,
    "NumberBathrooms": 1,
    "PropertyTypeId": "4F426DDE-E40C-4819-97B5-AEF5F94A5D53",
    "SalePrice": 250000.00,
    "RentPrice": 700.00,
    "SaleTax": 15.00,
    "IncomeTax": 10.00,
    "CodeInternal": "PCI0003005",
    "Year": 2012,
    "HasParking": true,
    "IsActive": true,
    "OwnerId": "38440EEA-FC9F-4B6F-B623-F72FDDC66A29"
  },
  {
    "Id": "FF980CA8-C717-4A30-9C9C-D72137443F6B",
    "Name": "Property-Name-3006",
    "Address": "Property-Address-3006",
    "Description": "Property-Description-3006-Sample-Data",
    "SquareMeter": 192.25,
    "NumberRooms": 3,
    "NumberBathrooms": 1,
    "PropertyTypeId": "35E9F237-FB6E-4E8E-B2C5-B5255C24801F",
    "SalePrice": 250000.00,
    "RentPrice": 700.00,
    "SaleTax": 15.00,
    "IncomeTax": 10.00,
    "CodeInternal": "PCI0003006",
    "Year": 2005,
    "HasParking": true,
    "IsActive": true,
    "OwnerId": "0C3A18AC-068D-41C2-BA37-4CA1BCD6F9F7"
  },
  {
    "Id": "BD28E62B-B943-4F2E-A7ED-699FDBEC8DD7",
    "Name": "Property-Name-3007",
    "Address": "Property-Address-3007",
    "Description": "Property-Description-3007-Sample-Data",
    "SquareMeter": 192.25,
    "NumberRooms": 3,
    "NumberBathrooms": 1,
    "PropertyTypeId": "F4E25DF1-82C4-4685-91AC-7305F6EB9ADD",
    "SalePrice": 250000.00,
    "RentPrice": 700.00,
    "SaleTax": 15.00,
    "IncomeTax": 10.00,
    "CodeInternal": "PCI0003007",
    "Year": 2008,
    "HasParking": false,
    "IsActive": true,
    "OwnerId": "6449C449-59DA-4C60-9AB2-1B9949024C86"
  },
  {
    "Id": "13F934B9-8073-41EB-8B7D-B90F441D8F58",
    "Name": "Property-Name-3008",
    "Address": "Property-Address-3008",
    "Description": "Property-Description-3008-Sample-Data",
    "SquareMeter": 192.25,
    "NumberRooms": 3,
    "NumberBathrooms": 1,
    "PropertyTypeId": "92E2453A-7D2F-44A4-A9FB-3E11ED3BB458",
    "SalePrice": 250000.00,
    "RentPrice": 700.00,
    "SaleTax": 15.00,
    "IncomeTax": 10.00,
    "CodeInternal": "PCI0003008",
    "Year": 2012,
    "HasParking": true,
    "IsActive": true,
    "OwnerId": "41C43138-9280-4EDC-9307-BEBE359796A5"
  },
  {
    "Id": "EEB14761-399E-477A-8F2D-92BF08465DEF",
    "Name": "Property-Name-3009",
    "Address": "Property-Address-3009",
    "Description": "Property-Description-3009-Sample-Data",
    "SquareMeter": 192.25,
    "NumberRooms": 3,
    "NumberBathrooms": 1,
    "PropertyTypeId": "C82043A7-1C2A-46B7-A0BF-82CD04674EB2",
    "SalePrice": 250000.00,
    "RentPrice": 700.00,
    "SaleTax": 15.00,
    "IncomeTax": 10.00,
    "CodeInternal": "PCI0003009",
    "Year": 2014,
    "HasParking": false,
    "IsActive": true,
    "OwnerId": "8B7CECC3-E157-419A-AA14-99D5A3C934A0"
  },
  {
    "Id": "A8BAA6C4-A6CE-4E4F-9E26-A660F3738866",
    "Name": "Property-Name-3010",
    "Address": "Property-Address-3010",
    "Description": "Property-Description-3010-Sample-Data",
    "SquareMeter": 192.25,
    "NumberRooms": 3,
    "NumberBathrooms": 1,
    "PropertyTypeId": "35E9F237-FB6E-4E8E-B2C5-B5255C24801F",
    "SalePrice": 250000.00,
    "RentPrice": 700.00,
    "SaleTax": 15.00,
    "IncomeTax": 10.00,
    "CodeInternal": "PCI0003010",
    "Year": 2007,
    "HasParking": true,
    "IsActive": true,
    "OwnerId": "E5C3D9B5-5988-48C6-96A3-02E680E48234"
  },
  {
    "Id": "2195A140-71B4-428B-8467-F669C9A731C0",
    "Name": "Property-Name-50010",
    "Address": "Property-Address-50010",
    "Description": "Property-Description-50010-Sample-Data",
    "SquareMeter": 192.25,
    "NumberRooms": 3,
    "NumberBathrooms": 1,
    "PropertyTypeId": "2E191A01-5623-4C92-B9DF-811955F990E8",
    "SalePrice": 250000.00,
    "RentPrice": 700.00,
    "SaleTax": 15.00,
    "IncomeTax": 10.00,
    "CodeInternal": "PCI0050010",
    "Year": 2015,
    "HasParking": true,
    "IsActive": true,
    "OwnerId": "8B7CECC3-E157-419A-AA14-99D5A3C934A0"
  },
  {
    "Id": "EE3C54D6-6781-47C1-AC98-3359FF93F19E",
    "Name": "Property-Name-50011",
    "Address": "Property-Address-50011",
    "Description": "Property-Description-50011-Sample-Data",
    "SquareMeter": 192.25,
    "NumberRooms": 3,
    "NumberBathrooms": 1,
    "PropertyTypeId": "35E9F237-FB6E-4E8E-B2C5-B5255C24801F",
    "SalePrice": 250000.00,
    "RentPrice": 700.00,
    "SaleTax": 15.00,
    "IncomeTax": 10.00,
    "CodeInternal": "PCI0050011",
    "Year": 2018,
    "HasParking": true,
    "IsActive": true,
    "OwnerId": "E5C3D9B5-5988-48C6-96A3-02E680E48234"
  }
]
